ln_jupyter_extra/_version.py
ln_jupyter_extra_wbhe-1.0.3.data/data/share/jupyter/labextensions/ln-jupyter-extra/install.json
ln_jupyter_extra_wbhe-1.0.3.dist-info/METADATA
ln_jupyter_extra_wbhe-1.0.3.dist-info/WHEEL
ln_jupyter_extra_wbhe-1.0.3.dist-info/licenses/LICENSE
ln_jupyter_extra_wbhe-1.0.3.dist-info/RECORD
